aws_recommendation_a9/__init__.py
aws_recommendation_a9/cloudwatch.py
aws_recommendation_a9/cost_estimations.py
aws_recommendation_a9/dynamodb.py
aws_recommendation_a9/ebs.py
aws_recommendation_a9/ec2.py
aws_recommendation_a9/elb.py
aws_recommendation_a9/kms.py
aws_recommendation_a9/rds.py
aws_recommendation_a9/recommendation.py
aws_recommendation_a9/redshift.py
aws_recommendation_a9/s3.py
aws_recommendation_a9/truted_advisor.py
aws_recommendation_a9/utils.py
aws_recommendation_a10-0.0.22.dist-info/LICENCE
aws_recommendation_a10-0.0.22.dist-info/METADATA
aws_recommendation_a10-0.0.22.dist-info/WHEEL
aws_recommendation_a10-0.0.22.dist-info/top_level.txt
aws_recommendation_a10-0.0.22.dist-info/RECORD
